BotAuth/BotAuth.py
BotAuth/__init__.py
BottleAuth-21.9.7.dist-info/LICENSE.txt
BottleAuth-21.9.7.dist-info/METADATA
BottleAuth-21.9.7.dist-info/WHEEL
BottleAuth-21.9.7.dist-info/top_level.txt
BottleAuth-21.9.7.dist-info/RECORD
