Metadata-Version: 2.1
Name: BottleAuth
Version: 21.9.7
Summary: Authentication and Authorization module for Bottle Web Apps
Home-page: https://github.com/Glocktober/BottleAuth
Author: gunville
Author-email: rk13088@yahoo.com
License: UNKNOWN
Project-URL: repo, https://github.com/Glocktober/BottleAuth
Project-URL: overview, https://github.com/Glocktober/BottleAuth/blob/main/README.md
Keywords: 'bottle CAS SAML OIDC plugin'
Platform: UNKNOWN
Classifier: Programming Language :: Python :: 3
Classifier: License :: OSI Approved :: MIT License
Classifier: Operating System :: OS Independent
Classifier: Framework :: Bottle
Requires-Python: >=3.6
License-File: LICENSE.txt
Requires-Dist: bottle (>=0.12.0)
Requires-Dist: BottleSessions (>=21.07.01)
